AUTHORS
COPYING
ChangeLog
MANIFEST.in
Makefile
README.rst
requirements.txt
setup.cfg
setup.py
container/Makefile
container/README.rst
container/build-lago-container.sh
container/el7-systemd/Dockerfile
container/el7-systemd-lago/Dockerfile.in
container/el7-systemd-lago/deploy.sh
container/el7-systemd-libvirt/Dockerfile.in
container/scripts/lago.sh
container/scripts/run-lago-container.sh
etc/polkit/lago.pkla
etc/sudo/lago
lago/__init__.py
lago/brctl.py
lago/build.py
lago/cmd.py
lago/config.py
lago/constants.py
lago/export.py
lago/guestfs_tools.py
lago/lago_ansible.py
lago/log_utils.py
lago/paths.py
lago/prefix.py
lago/sdk.py
lago/sdk_utils.py
lago/service.py
lago/ssh.py
lago/subnet_lease.py
lago/sysprep.py
lago/templates.py
lago/utils.py
lago/validation.py
lago/virt.py
lago/vm.py
lago/workdir.py
lago.egg-info/PKG-INFO
lago.egg-info/SOURCES.txt
lago.egg-info/dependency_links.txt
lago.egg-info/entry_points.txt
lago.egg-info/not-zip-safe
lago.egg-info/pbr.json
lago.egg-info/requires.txt
lago.egg-info/top_level.txt
lago/plugins/__init__.py
lago/plugins/cli.py
lago/plugins/output.py
lago/plugins/service.py
lago/plugins/vm.py
lago/providers/__init__.py
lago/providers/libvirt/__init__.py
lago/providers/libvirt/cpu.py
lago/providers/libvirt/network.py
lago/providers/libvirt/utils.py
lago/providers/libvirt/vm.py
lago/providers/libvirt/templates/dom_template-base.xml.j2
lago/providers/libvirt/templates/dom_template-el6.xml.j2
lago/providers/libvirt/templates/net_br_template.xml
lago/providers/libvirt/templates/net_nat_template.xml
lago/providers/libvirt/templates/snapshot_template.xml
lago/templates/sysprep-base.j2
lago/templates/sysprep-debian.j2
lago/templates/sysprep-el6.j2
lago/templates/sysprep-el7.j2
lago/templates/sysprep-fc24.j2
lago/templates/sysprep-fc25.j2
lago/templates/sysprep-fc26.j2
lago/templates/sysprep-macros.j2