Metadata-Version: 1.1
Name: lago
Version: 0.45.0
Summary: Deploy and tear down environments of several virtual machines
Home-page: https://github.com/lago-project/lago
Author: David Caro and Lago developers
Author-email: lago-devel@ovirt.org
License: GNU GPLv2+
Keywords: virtualization
Platform: Linux
Classifier: Operating System :: POSIX :: Linux
Classifier: Programming Language :: Python :: 2.7
Classifier: License :: OSI Approved :: GNU General Public License v2 (GPLv2)
